Workbook

Sheet Assumptions
B2: AJ VITANZA DEBUT TEE — DROP ECONOMICS
B3: Every blue cell is an input you can change. Black cells are formulas — do not type over them.
B5: WHAT WAS SPENT
B6: Total already paid by AJ (design, sample, production) | C6: 4800 | D6: From Louis. Covers designs, sample and the full print run. Sunk — already spent.
B7: Total shirts printed | C7: =SUM(Inventory!C6:C10) -> 194 | D7: Pulled from the Inventory tab so the two can never disagree.
B8: Cost per shirt | C8: =IF(C7=0,0,C6/C7) -> 24.742268 | D8: Total spend spread across the run. Bookkeeping only — the money is already gone.
B10: WHAT YOU CHARGE
B11: Shirt price | C11: 50 | D11: Same price online and at the merch table.
B12: Shipping charged (US) | C12: 6 | D12: The US Standard rate set on all five Stripe payment links.
B14: WHAT EACH ONLINE ORDER ACTUALLY COSTS YOU
B15: Stripe % fee | C15: 0.029 | D15: Stripe's standard US online card rate. Applies to shipping too, not just the shirt.
B16: Stripe fixed fee per order | C16: 0.3 | D16: Charged once per transaction regardless of order size.
B17: Actual postage you pay (US) | C17: 6 | D17: ESTIMATE — USPS Ground Advantage, sub-1lb parcel. Replace with your real label cost once you print a few.
B18: Packaging per order (mailer + label) | C18: 0.5 | D18: ESTIMATE. Replace with the real per-bag cost from the shipment bags arriving tomorrow.
B20: WHAT EACH SHOW SALE COSTS YOU
B21: Share of show sales taken by card (vs cash) | C21: 0.5 | D21: Guess. 0% = all cash, 100% = all card. Cash keeps the full $50.
B22: Stripe in-person % fee | C22: 0.027 | D22: Tap to Pay / Terminal rate. Lower than online because the card is present.
B23: Stripe in-person fixed fee | C23: 0.05 | D23: Per in-person transaction.
B25: NET PER SHIRT — THE NUMBERS THAT MATTER
B26: Net per ONLINE order (after fees, postage, packaging) | C26: =(C11+C12)-((C11+C12)*C15+C16)-C17-C18 -> 47.576 | D26: Customer pays shirt + shipping. Subtract Stripe fee on the whole charge, then your real postage and packaging.
B27: Net per SHOW sale (blended cash/card) | C27: =C11-(C21*(C11*C22+C23)) -> 49.3 | D27: No shipping, no packaging. Only the card share pays a fee.
B29: Note on international orders | D29: International is priced at $35 shipping against roughly $19-$40 of real postage depending on destination. Treat it as break-even at best. This model assumes US orders only — if a lot of international comes in, lower the "Actual postage" input to see the damage.
B32: HOW TO READ THIS WORKBOOK
B33: Blue text = you type here
B34: Yellow fill = assumption worth checking against reality
B35: Black text = a formula. Leave it alone.
B36: Green text = pulled from another tab.
B38: Day to day, you only touch the Tracker tab.

Sheet Inventory
B2: INVENTORY & PRESALE ALLOCATION
B3: Blue = counted in the garage and typed into Stripe. Keep column D matching the payment caps on the five links.
B5: Size | C5: In stock | D5: Presale cap | E5: Held for show | F5: Presale value | G5: Show value
B6: XS | C6: 10 | D6: 3 | E6: =C6-D6 -> 7 | F6: =D6*Assumptions!$C$26 -> 142.728 | G6: =E6*Assumptions!$C$27 -> 345.1
B7: S | C7: 65 | D7: 17 | E7: =C7-D7 -> 48 | F7: =D7*Assumptions!$C$26 -> 808.792 | G7: =E7*Assumptions!$C$27 -> 2366.4
B8: M | C8: 62 | D8: 16 | E8: =C8-D8 -> 46 | F8: =D8*Assumptions!$C$26 -> 761.216 | G8: =E8*Assumptions!$C$27 -> 2267.8
B9: L | C9: 43 | D9: 11 | E9: =C9-D9 -> 32 | F9: =D9*Assumptions!$C$26 -> 523.336 | G9: =E9*Assumptions!$C$27 -> 1577.6
B10: XL | C10: 14 | D10: 3 | E10: =C10-D10 -> 11 | F10: =D10*Assumptions!$C$26 -> 142.728 | G10: =E10*Assumptions!$C$27 -> 542.3
B11: TOTAL | C11: =SUM(C6:C10) -> 194 | D11: =SUM(D6:D10) -> 50 | E11: =SUM(E6:E10) -> 144 | F11: =SUM(F6:F10) -> 2378.8 | G11: =SUM(G6:G10) -> 7099.2
B13: Presale caps must sum to 50 — that is what the website counter says.
B14: =IF(D11=50,"OK - caps sum to 50","MISMATCH - caps sum to "&D11&", website says 50") -> OK - caps sum to 50
B16: XS (10 units) and XL (14 units) are the thin sizes. A presale cap of 3 each keeps a real reserve for the merch table.

Sheet Break-even
B2: BREAK-EVEN: HOW MANY SHIRTS TO GET THE $4,800 BACK
B4: IF EVERY SHIRT SOLD ONLINE
B5: Net per online order | C5: =Assumptions!C26 -> 47.576
B6: Shirts needed to break even | C6: =IF(C5<=0,"never",ROUNDUP(Assumptions!C6/C5,0)) -> 101 | D6: Worst realistic case — you pay Stripe, postage and packaging on every single unit.
B8: IF EVERY SHIRT SOLD AT THE SHOW
B9: Net per show sale | C9: =Assumptions!C27 -> 49.3
B10: Shirts needed to break even | C10: =IF(C9<=0,"never",ROUNDUP(Assumptions!C6/C9,0)) -> 98 | D10: Best case — no shipping, no packaging, and cash sales pay no fee at all.
B12: THE ACTUAL PLAN: 50 ONLINE, THE REST AT THE SHOW
B13: Presale units | C13: =Inventory!D11 -> 50
B14: Cash in from a sold-out presale | C14: =C13*C5 -> 2378.8
B15: Share of the $4,800 that recovers | C15: =IF(Assumptions!C6=0,0,C14/Assumptions!C6) -> 0.49558333
B16: Still to recover after the presale | C16: =MAX(0,Assumptions!C6-C14) -> 2421.2
B17: Show sales needed to finish paying it off | C17: =IF(C9<=0,"never",ROUNDUP(C16/C9,0)) -> 50
B18: TOTAL SHIRTS TO BREAK EVEN | C18: =C13+C17 -> 100
B19: As a share of the whole run | C19: =IF(Assumptions!C7=0,0,C18/Assumptions!C7) -> 0.51546392
B21: IF THE WHOLE RUN SELLS
B22: Presale revenue (net) | C22: =Inventory!F11 -> 2378.8
B23: Show revenue (net) | C23: =Inventory!G11 -> 7099.2
B24: Total net revenue | C24: =C22+C23 -> 9478
B25: Less what AJ already spent | C25: =-Assumptions!C6 -> -4800
B26: PROFIT ON A FULL SELL-THROUGH | C26: =C24+C25 -> 4678
B27: Return on the $4,800 | C27: =IF(Assumptions!C6=0,0,C24/Assumptions!C6) -> 1.9745833

Sheet Tracker
B2: LIVE SALES TRACKER
B3: Update the two blue columns as orders come in. Everything else follows.
B5: Size | C5: Presale cap | D5: Sold online | E5: Sold at show | F5: Presale left | G5: Total sold | H5: Net cash in
B6: XS | C6: =Inventory!D6 -> 3 | D6: 0 | E6: 0 | F6: =MAX(0,C6-D6) -> 3 | G6: =D6+E6 -> 0 | H6: =D6*Assumptions!$C$26+E6*Assumptions!$C$27 -> 0
B7: S | C7: =Inventory!D7 -> 17 | D7: 0 | E7: 0 | F7: =MAX(0,C7-D7) -> 17 | G7: =D7+E7 -> 0 | H7: =D7*Assumptions!$C$26+E7*Assumptions!$C$27 -> 0
B8: M | C8: =Inventory!D8 -> 16 | D8: 0 | E8: 0 | F8: =MAX(0,C8-D8) -> 16 | G8: =D8+E8 -> 0 | H8: =D8*Assumptions!$C$26+E8*Assumptions!$C$27 -> 0
B9: L | C9: =Inventory!D9 -> 11 | D9: 0 | E9: 0 | F9: =MAX(0,C9-D9) -> 11 | G9: =D9+E9 -> 0 | H9: =D9*Assumptions!$C$26+E9*Assumptions!$C$27 -> 0
B10: XL | C10: =Inventory!D10 -> 3 | D10: 0 | E10: 0 | F10: =MAX(0,C10-D10) -> 3 | G10: =D10+E10 -> 0 | H10: =D10*Assumptions!$C$26+E10*Assumptions!$C$27 -> 0
B11: TOTAL | C11: =SUM(C6:C10) -> 50 | D11: =SUM(D6:D10) -> 0 | E11: =SUM(E6:E10) -> 0 | F11: =SUM(F6:F10) -> 50 | G11: =SUM(G6:G10) -> 0 | H11: =SUM(H6:H10) -> 0
B13: Recovered so far | C13: =IF(Assumptions!C6=0,0,H11/Assumptions!C6) -> 0 | I13: Share of the $4,800 back in the bank.
B14: Still to recover | C14: =MAX(0,Assumptions!C6-H11) -> 4800
B15: Profit / (loss) so far | C15: =H11-Assumptions!C6 -> -4800 | I15: Goes positive the moment you clear break-even.
B17: Status | C17: =IF(H11>=Assumptions!C6,"PAID OFF - every shirt from here is profit","Need "&ROUNDUP(C14/Assumptions!C27,0)&" more show sales to break even") -> Need 98 more show sales to break even
B19: EXAMPLE — delete this row once real orders start
B20: M | C20: 16 | D20: 9 | E20: 0 | F20: 7 | G20: 9 | H20: =D20*Assumptions!$C$26+E20*Assumptions!$C$27 -> 428.184 | I20: Nine M sold online, none at the show yet, seven of the presale allocation left.
